hassbridge/__init__.py
hassbridge/cli.py
hassbridge/hassinterface.py
hassbridge/mprismain.py
hassbridge/playerinterface.py
homeassistant_mpris_bridge-0.0.2.dist-info/entry_points.txt
homeassistant_mpris_bridge-0.0.2.dist-info/WHEEL
homeassistant_mpris_bridge-0.0.2.dist-info/METADATA
homeassistant_mpris_bridge-0.0.2.dist-info/RECORD
