Metadata-Version: 2.1
Name: homeassistant-mpris-bridge
Version: 0.0.2
Summary: Control your Home Assistant media players using MPRIS
Home-page: https://github.com/rytilahti/homeassistant-mpris-bridge
License: GPL-3.0-or-later
Author: Teemu R.
Author-email: tpr@iki.fi
Requires-Python: >=3.8,<4.0
Classifier: Development Status :: 3 - Alpha
Classifier: Environment :: Console
Classifier: Intended Audience :: End Users/Desktop
Classifier: License :: OSI Approved :: GNU General Public License v3 or later (GPLv3+)
Classifier: Operating System :: OS Independent
Classifier: Programming Language :: Python :: 3
Classifier: Programming Language :: Python :: 3.10
Classifier: Programming Language :: Python :: 3.8
Classifier: Programming Language :: Python :: 3.9
Classifier: Topic :: Home Automation
Requires-Dist: anyio
Requires-Dist: asyncclick (>=7)
Requires-Dist: dbus_next (>=0.1.3)
Requires-Dist: websockets (>=10.0)
Project-URL: Repository, https://github.com/rytilahti/homeassistant-mpris-bridge
